.gitignore
.readthedocs.yaml
LICENSE
README.md
pyproject.toml
.github/workflows/python-publish.yml
docs/abbrev_long.bib
docs/conf.py
docs/index.rst
docs/modules.rst
docs/references.bib
docs/_static/images/example.gif
docs/_static/images/image.png
docs/_static/images/image_example.jpg
docs/_static/images/on_image.png
docs/_static/images/on_image_fit.png
docs/_static/images/overlay_after_rot1.png
docs/_static/images/overlay_after_rot1_shape.png
docs/_static/images/overlay_after_rot2.png
docs/_static/images/overlay_after_rot2_shape.png
docs/_static/images/overlay_after_rot3.png
docs/_static/images/parts_overlay1.png
docs/_static/images/parts_overlay1_rot.png
docs/_static/images/parts_overlay2.png
docs/_static/images/parts_overlay2_rot.png
docs/_static/images/pose3d.png
docs/_static/images/pose3d_parts_color.png
docs/_static/images/pose3d_parts_color_blown.png
docs/_static/images/tmean_parts.png
docs/_static/images/tmean_parts_blown.png
docs/_static/styles/my_theme.css
docs/_templates/copyright.html
docs/_templates/autoapi/index.rst
docs/_templates/autoapi/python/attribute.rst
docs/_templates/autoapi/python/class.rst
docs/_templates/autoapi/python/data.rst
docs/_templates/autoapi/python/exception.rst
docs/_templates/autoapi/python/function.rst
docs/_templates/autoapi/python/method.rst
docs/_templates/autoapi/python/module.rst
docs/_templates/autoapi/python/package.rst
docs/_templates/autoapi/python/property.rst
src/smplfitter/__init__.py
src/smplfitter/_version.py
src/smplfitter/common.py
src/smplfitter.egg-info/PKG-INFO
src/smplfitter.egg-info/SOURCES.txt
src/smplfitter.egg-info/dependency_links.txt
src/smplfitter.egg-info/requires.txt
src/smplfitter.egg-info/top_level.txt
src/smplfitter/decimation/__init__.py
src/smplfitter/decimation/decimate_body_models.py
src/smplfitter/decimation/make_post_lbs_joint_regressors.py
src/smplfitter/decimation/make_post_lbs_joint_regressors_tf.py
src/smplfitter/np/__init__.py
src/smplfitter/np/bodyfitter.py
src/smplfitter/np/bodymodel.py
src/smplfitter/np/lstsq.py
src/smplfitter/np/rotation.py
src/smplfitter/np/util.py
src/smplfitter/pt/__init__.py
src/smplfitter/pt/bodyconverter.py
src/smplfitter/pt/bodyfitter.py
