Metadata-Version: 2.4
Name: smplfitter
Version: 0.2.10
Summary: Fast inverse kinematics and shape fitting for SMPL-family models in NumPy, PyTorch, and TensorFlow
Author-email: István Sárándi <istvan.sarandi@uni-tuebingen.de>
License: MIT License
Project-URL: Homepage, https://github.com/isarandi/smplfitter
Project-URL: Repository, https://github.com/isarandi/smplfitter
Project-URL: Issues, https://github.com/isarandi/smplfitter/issues
Project-URL: Author, https://istvansarandi.com
Requires-Python: >=3.6
License-File: LICENSE
Requires-Dist: numpy
Requires-Dist: scipy
Requires-Dist: chumpy
Provides-Extra: tensorflow
Requires-Dist: tensorflow; extra == "tensorflow"
Provides-Extra: pytorch
Requires-Dist: torch; extra == "pytorch"
Provides-Extra: keywords
Requires-Dist: smpl; extra == "keywords"
Requires-Dist: smplx; extra == "keywords"
Requires-Dist: smplh; extra == "keywords"
Requires-Dist: 3d-human; extra == "keywords"
Requires-Dist: body-model; extra == "keywords"
Requires-Dist: ik; extra == "keywords"
Requires-Dist: inverse-kinematics; extra == "keywords"
Requires-Dist: parametric-model; extra == "keywords"
Requires-Dist: pose-estimation; extra == "keywords"
Requires-Dist: differentiable; extra == "keywords"
Requires-Dist: gpu; extra == "keywords"
Requires-Dist: tensorflow; extra == "keywords"
Requires-Dist: pytorch; extra == "keywords"
Requires-Dist: numpy; extra == "keywords"
Requires-Dist: batch-processing; extra == "keywords"
Dynamic: license-file
